Metadata-Version: 1.0
Name: abtools
Version: 0.1.10
Summary: Utilities for analysis of antibody NGS data
Home-page: https://www.github.com/briney/abtools
Author: Bryan Briney
Author-email: briney@scripps.edu
License: UNKNOWN
Platform: UNKNOWN
